{"version":3,"kind":"Article","sha256":"192682585927dbe31c71e2f9b39688aaf5caa057e00aec5ba7bc32cef5e0e8f6","slug":"sections.computer-programming.fortran.dfft.dfft","location":"/Sections/Computer_Programming/Fortran/DFFT/DFFT.md","dependencies":[],"frontmatter":{"title":"Discretized Fourier Transform of Arbitrary Signal Using FFTW3 in Fortran","content_includes_title":false,"authors":[{"nameParsed":{"literal":"Mark Khusid","given":"Mark","family":"Khusid"},"name":"Mark Khusid","id":"contributors-myst-generated-uid-0"}],"github":"https://github.com/markkhusid/MKDynamics_Website_V2","numbering":{"title":{"offset":3}},"source_url":"https://github.com/markkhusid/MKDynamics_Website_V2/blob/master/Sections/Computer_Programming/Fortran/DFFT/DFFT.md","edit_url":"https://github.com/markkhusid/MKDynamics_Website_V2/edit/master/Sections/Computer_Programming/Fortran/DFFT/DFFT.md","thumbnail":"/build/sine_wave2_10Hz-49299ad41b3b21d8c987f46d4cd10d3f.jpeg","exports":[{"format":"md","filename":"DFFT.md","url":"/build/DFFT-d79b51946410e2603df1e620ccdda1bf.md"}]},"mdast":{"type":"root","children":[{"type":"block","children":[{"type":"heading","depth":2,"position":{"start":{"line":3,"column":1},"end":{"line":3,"column":1}},"children":[{"type":"text","value":"Table of Contents","position":{"start":{"line":3,"column":1},"end":{"line":3,"column":1}},"key":"dSVAWradk7"}],"identifier":"table-of-contents","label":"Table of Contents","html_id":"table-of-contents","implicit":true,"key":"PZ87JOOTVQ"},{"type":"heading","depth":2,"position":{"start":{"line":5,"column":1},"end":{"line":5,"column":1}},"children":[{"type":"text","value":"Introduction","position":{"start":{"line":5,"column":1},"end":{"line":5,"column":1}},"key":"V0YA1oGUde"}],"identifier":"introduction","label":"Introduction","html_id":"introduction","implicit":true,"key":"DeZ7cewmad"},{"type":"paragraph","position":{"start":{"line":6,"column":1},"end":{"line":6,"column":1}},"children":[{"type":"text","value":"The Discrete Fourier Transform (DFT) is a mathematical technique used to convert a signal from its time domain representation to its frequency domain representation. The DFT is defined as follows:","position":{"start":{"line":6,"column":1},"end":{"line":6,"column":1}},"key":"iAGD6rJyPB"}],"key":"W8r9hQXTsM"},{"type":"math","value":"X(k) = \\sum_{n=0}^{N-1} x(n) e^{-j2\\pi kn/N}","position":{"start":{"line":8,"column":1},"end":{"line":10,"column":1}},"html":"<span class=\"katex-display\"><span class=\"katex\"><span class=\"katex-mathml\"><math xmlns=\"http://www.w3.org/1998/Math/MathML\" display=\"block\"><semantics><mrow><mi>X</mi><mo stretchy=\"false\">(</mo><mi>k</mi><mo stretchy=\"false\">)</mo><mo>=</mo><munderover><mo>∑</mo><mrow><mi>n</mi><mo>=</mo><mn>0</mn></mrow><mrow><mi>N</mi><mo>−</mo><mn>1</mn></mrow></munderover><mi>x</mi><mo stretchy=\"false\">(</mo><mi>n</mi><mo stretchy=\"false\">)</mo><msup><mi>e</mi><mrow><mo>−</mo><mi>j</mi><mn>2</mn><mi>π</mi><mi>k</mi><mi>n</mi><mi mathvariant=\"normal\">/</mi><mi>N</mi></mrow></msup></mrow><annotation encoding=\"application/x-tex\">X(k) = \\sum_{n=0}^{N-1} x(n) e^{-j2\\pi kn/N}</annotation></semantics></math></span><span class=\"katex-html\" aria-hidden=\"true\"><span class=\"base\"><span class=\"strut\" style=\"height:1em;vertical-align:-0.25em;\"></span><span class=\"mord mathnormal\" style=\"margin-right:0.07847em;\">X</span><span class=\"mopen\">(</span><span class=\"mord mathnormal\" style=\"margin-right:0.03148em;\">k</span><span class=\"mclose\">)</span><span class=\"mspace\" style=\"margin-right:0.2778em;\"></span><span class=\"mrel\">=</span><span class=\"mspace\" style=\"margin-right:0.2778em;\"></span></span><span class=\"base\"><span class=\"strut\" style=\"height:3.0954em;vertical-align:-1.2671em;\"></span><span class=\"mop op-limits\"><span class=\"vlist-t vlist-t2\"><span class=\"vlist-r\"><span class=\"vlist\" style=\"height:1.8283em;\"><span style=\"top:-1.8829em;margin-left:0em;\"><span class=\"pstrut\" style=\"height:3.05em;\"></span><span class=\"sizing reset-size6 size3 mtight\"><span class=\"mord mtight\"><span class=\"mord mathnormal mtight\">n</span><span class=\"mrel mtight\">=</span><span class=\"mord mtight\">0</span></span></span></span><span style=\"top:-3.05em;\"><span class=\"pstrut\" style=\"height:3.05em;\"></span><span><span class=\"mop op-symbol large-op\">∑</span></span></span><span style=\"top:-4.3em;margin-left:0em;\"><span class=\"pstrut\" style=\"height:3.05em;\"></span><span class=\"sizing reset-size6 size3 mtight\"><span class=\"mord mtight\"><span class=\"mord mathnormal mtight\" style=\"margin-right:0.10903em;\">N</span><span class=\"mbin mtight\">−</span><span class=\"mord mtight\">1</span></span></span></span></span><span class=\"vlist-s\">​</span></span><span class=\"vlist-r\"><span class=\"vlist\" style=\"height:1.2671em;\"><span></span></span></span></span></span><span class=\"mspace\" style=\"margin-right:0.1667em;\"></span><span class=\"mord mathnormal\">x</span><span class=\"mopen\">(</span><span class=\"mord mathnormal\">n</span><span class=\"mclose\">)</span><span class=\"mord\"><span class=\"mord mathnormal\">e</span><span class=\"msupsub\"><span class=\"vlist-t\"><span class=\"vlist-r\"><span class=\"vlist\" style=\"height:0.938em;\"><span style=\"top:-3.113em;margin-right:0.05em;\"><span class=\"pstrut\" style=\"height:2.7em;\"></span><span class=\"sizing reset-size6 size3 mtight\"><span class=\"mord mtight\"><span class=\"mord mtight\">−</span><span class=\"mord mathnormal mtight\" style=\"margin-right:0.05724em;\">j</span><span class=\"mord mtight\">2</span><span class=\"mord mathnormal mtight\">πkn</span><span class=\"mord mtight\">/</span><span class=\"mord mathnormal mtight\" style=\"margin-right:0.10903em;\">N</span></span></span></span></span></span></span></span></span></span></span></span></span>","enumerator":"1","key":"sbE5IR8Uxp"},{"type":"paragraph","position":{"start":{"line":12,"column":1},"end":{"line":12,"column":1}},"children":[{"type":"text","value":"where ","position":{"start":{"line":12,"column":1},"end":{"line":12,"column":1}},"key":"Huq078vX5N"},{"type":"inlineMath","value":"X(k)","position":{"start":{"line":12,"column":1},"end":{"line":12,"column":1}},"html":"<span class=\"katex\"><span class=\"katex-mathml\"><math xmlns=\"http://www.w3.org/1998/Math/MathML\"><semantics><mrow><mi>X</mi><mo stretchy=\"false\">(</mo><mi>k</mi><mo stretchy=\"false\">)</mo></mrow><annotation encoding=\"application/x-tex\">X(k)</annotation></semantics></math></span><span class=\"katex-html\" aria-hidden=\"true\"><span class=\"base\"><span class=\"strut\" style=\"height:1em;vertical-align:-0.25em;\"></span><span class=\"mord mathnormal\" style=\"margin-right:0.07847em;\">X</span><span class=\"mopen\">(</span><span class=\"mord mathnormal\" style=\"margin-right:0.03148em;\">k</span><span class=\"mclose\">)</span></span></span></span>","key":"zAA8r9GsL5"},{"type":"text","value":" is the DFT of the signal ","position":{"start":{"line":12,"column":1},"end":{"line":12,"column":1}},"key":"r5iLp3Vb07"},{"type":"inlineMath","value":"x(n)","position":{"start":{"line":12,"column":1},"end":{"line":12,"column":1}},"html":"<span class=\"katex\"><span class=\"katex-mathml\"><math xmlns=\"http://www.w3.org/1998/Math/MathML\"><semantics><mrow><mi>x</mi><mo stretchy=\"false\">(</mo><mi>n</mi><mo stretchy=\"false\">)</mo></mrow><annotation encoding=\"application/x-tex\">x(n)</annotation></semantics></math></span><span class=\"katex-html\" aria-hidden=\"true\"><span class=\"base\"><span class=\"strut\" style=\"height:1em;vertical-align:-0.25em;\"></span><span class=\"mord mathnormal\">x</span><span class=\"mopen\">(</span><span class=\"mord mathnormal\">n</span><span class=\"mclose\">)</span></span></span></span>","key":"pddFmJKlTe"},{"type":"text","value":", ","position":{"start":{"line":12,"column":1},"end":{"line":12,"column":1}},"key":"S2iEZAWeg4"},{"type":"inlineMath","value":"N","position":{"start":{"line":12,"column":1},"end":{"line":12,"column":1}},"html":"<span class=\"katex\"><span class=\"katex-mathml\"><math xmlns=\"http://www.w3.org/1998/Math/MathML\"><semantics><mrow><mi>N</mi></mrow><annotation encoding=\"application/x-tex\">N</annotation></semantics></math></span><span class=\"katex-html\" aria-hidden=\"true\"><span class=\"base\"><span class=\"strut\" style=\"height:0.6833em;\"></span><span class=\"mord mathnormal\" style=\"margin-right:0.10903em;\">N</span></span></span></span>","key":"cSTKPBJmp0"},{"type":"text","value":" is the number of samples in the signal, and ","position":{"start":{"line":12,"column":1},"end":{"line":12,"column":1}},"key":"n7praJE2ZS"},{"type":"inlineMath","value":"k","position":{"start":{"line":12,"column":1},"end":{"line":12,"column":1}},"html":"<span class=\"katex\"><span class=\"katex-mathml\"><math xmlns=\"http://www.w3.org/1998/Math/MathML\"><semantics><mrow><mi>k</mi></mrow><annotation encoding=\"application/x-tex\">k</annotation></semantics></math></span><span class=\"katex-html\" aria-hidden=\"true\"><span class=\"base\"><span class=\"strut\" style=\"height:0.6944em;\"></span><span class=\"mord mathnormal\" style=\"margin-right:0.03148em;\">k</span></span></span></span>","key":"Lv0yfCXA1u"},{"type":"text","value":" is the frequency index. The DFT is a powerful tool in signal processing and is used in a wide range of applications, including audio and image processing, communications, and control systems.","position":{"start":{"line":12,"column":1},"end":{"line":12,"column":1}},"key":"aUXGZyUyN7"}],"key":"dWvLpQAl8v"},{"type":"paragraph","position":{"start":{"line":14,"column":1},"end":{"line":14,"column":1}},"children":[{"type":"text","value":"The Fast Fourier Transform (FFT) is an algorithm that computes the DFT of a signal more efficiently than the standard DFT algorithm. The FFT algorithm exploits the symmetry properties of the DFT to reduce the number of computations required to compute the DFT. The FFT algorithm is widely used in practice due to its speed and efficiency.","position":{"start":{"line":14,"column":1},"end":{"line":14,"column":1}},"key":"oIHsbxWL1S"}],"key":"VyvF4YtF90"},{"type":"paragraph","position":{"start":{"line":16,"column":1},"end":{"line":16,"column":1}},"children":[{"type":"text","value":"In this tutorial, we will use the FFTW3 library to compute the DFT of an arbitrary signal. FFTW3 is a highly optimized library for computing the FFT of a signal and is widely used in scientific computing applications. We will demonstrate how to use the FFTW3 library to compute the DFT of a signal and visualize the frequency spectrum of the signal.","position":{"start":{"line":16,"column":1},"end":{"line":16,"column":1}},"key":"cNQm9VshUQ"}],"key":"rSGlhIQD6p"},{"type":"heading","depth":2,"position":{"start":{"line":18,"column":1},"end":{"line":18,"column":1}},"children":[{"type":"text","value":"Prerequisites","position":{"start":{"line":18,"column":1},"end":{"line":18,"column":1}},"key":"vi29zeIpay"}],"identifier":"prerequisites","label":"Prerequisites","html_id":"prerequisites","implicit":true,"key":"LBZKlraOsP"},{"type":"paragraph","position":{"start":{"line":19,"column":1},"end":{"line":19,"column":1}},"children":[{"type":"text","value":"To follow this tutorial, you will need:","position":{"start":{"line":19,"column":1},"end":{"line":19,"column":1}},"key":"fmVOtxMZkr"}],"key":"Vlq3w1yRRV"},{"type":"list","ordered":false,"spread":false,"position":{"start":{"line":20,"column":1},"end":{"line":23,"column":1}},"children":[{"type":"listItem","spread":true,"position":{"start":{"line":20,"column":1},"end":{"line":20,"column":1}},"children":[{"type":"paragraph","children":[{"type":"text","value":"A basic understanding of Fortran programming","position":{"start":{"line":20,"column":1},"end":{"line":20,"column":1}},"key":"Mr0JtOwIDb"}],"key":"wZ2XPtNT4B"}],"key":"bT4ZLTa6t8"},{"type":"listItem","spread":true,"position":{"start":{"line":21,"column":1},"end":{"line":21,"column":1}},"children":[{"type":"paragraph","children":[{"type":"text","value":"A working Fortran compiler (e.g., gfortran)","position":{"start":{"line":21,"column":1},"end":{"line":21,"column":1}},"key":"kVb4gwJMq2"}],"key":"mhiLMhSeHC"}],"key":"KdvWY4OJvz"},{"type":"listItem","spread":true,"position":{"start":{"line":22,"column":1},"end":{"line":23,"column":1}},"children":[{"type":"paragraph","children":[{"type":"text","value":"The FFTW3 library installed on your system","position":{"start":{"line":22,"column":1},"end":{"line":22,"column":1}},"key":"W1Zi62EL9R"}],"key":"TbZvVhQYl2"}],"key":"ccSVJMS9n9"}],"key":"x3VfUmApOm"},{"type":"heading","depth":2,"position":{"start":{"line":24,"column":1},"end":{"line":24,"column":1}},"children":[{"type":"text","value":"Installing FFTW3","position":{"start":{"line":24,"column":1},"end":{"line":24,"column":1}},"key":"OShDBbY8cy"}],"identifier":"installing-fftw3","label":"Installing FFTW3","html_id":"installing-fftw3","implicit":true,"key":"zWRnCZp47L"},{"type":"paragraph","position":{"start":{"line":25,"column":1},"end":{"line":25,"column":1}},"children":[{"type":"text","value":"The FFTW3 library is a free and open-source library that can be downloaded from the FFTW website. To install FFTW3 on your system, follow these steps:","position":{"start":{"line":25,"column":1},"end":{"line":25,"column":1}},"key":"ssmdIQ5AVS"}],"key":"jyA5cj4e8V"},{"type":"list","ordered":true,"start":1,"spread":false,"position":{"start":{"line":26,"column":1},"end":{"line":28,"column":1}},"children":[{"type":"listItem","spread":true,"position":{"start":{"line":26,"column":1},"end":{"line":26,"column":1}},"children":[{"type":"paragraph","children":[{"type":"text","value":"Download the FFTW3 library from the FFTW website.","position":{"start":{"line":26,"column":1},"end":{"line":26,"column":1}},"key":"SZ4LRROESr"}],"key":"lTwgK5Ns1h"}],"key":"ZYfDAQP3mC"},{"type":"listItem","spread":true,"position":{"start":{"line":27,"column":1},"end":{"line":27,"column":1}},"children":[{"type":"paragraph","children":[{"type":"text","value":"Extract the contents of the downloaded archive to a directory on your system.","position":{"start":{"line":27,"column":1},"end":{"line":27,"column":1}},"key":"yYjxe0NeyZ"}],"key":"XmbhOGTG71"}],"key":"tG2ItsZYh4"},{"type":"listItem","spread":true,"position":{"start":{"line":28,"column":1},"end":{"line":28,"column":1}},"children":[{"type":"paragraph","children":[{"type":"text","value":"Run the following commands to configure, compile, and install the FFTW3 library:","position":{"start":{"line":28,"column":1},"end":{"line":28,"column":1}},"key":"pHpkogGMlg"}],"key":"ifxpTQ1O0M"}],"key":"wuU67SqK0i"}],"key":"c9BvwR5ila"},{"type":"code","lang":"bash","value":"./configure\nmake\nmake install","position":{"start":{"line":29,"column":1},"end":{"line":33,"column":1}},"key":"CChz3ZIIw4"},{"type":"heading","depth":2,"position":{"start":{"line":35,"column":1},"end":{"line":35,"column":1}},"children":[{"type":"text","value":"Computing the DFT Using FFTW3","position":{"start":{"line":35,"column":1},"end":{"line":35,"column":1}},"key":"EtApdTPOSC"}],"identifier":"computing-the-dft-using-fftw3","label":"Computing the DFT Using FFTW3","html_id":"computing-the-dft-using-fftw3","implicit":true,"key":"Lq4FSet5uj"},{"type":"paragraph","position":{"start":{"line":36,"column":1},"end":{"line":36,"column":1}},"children":[{"type":"text","value":"To compute the DFT of an arbitrary signal using FFTW3, follow these steps:","position":{"start":{"line":36,"column":1},"end":{"line":36,"column":1}},"key":"XbFzYKKIyh"}],"key":"Xu9k5bF3ha"},{"type":"list","ordered":true,"start":1,"spread":false,"position":{"start":{"line":37,"column":1},"end":{"line":37,"column":1}},"children":[{"type":"listItem","spread":true,"position":{"start":{"line":37,"column":1},"end":{"line":37,"column":1}},"children":[{"type":"paragraph","children":[{"type":"text","value":"Include the FFTW3 module in your Fortran program:","position":{"start":{"line":37,"column":1},"end":{"line":37,"column":1}},"key":"pajaNATbn3"}],"key":"FiW4X5v0Ng"}],"key":"qS4RBl2SW3"}],"key":"OLcnkY83n3"},{"type":"code","lang":"fortran","value":"use, intrinsic :: iso_c_binding\nuse fftw3","position":{"start":{"line":38,"column":1},"end":{"line":41,"column":1}},"key":"YHQsPk8LjB"},{"type":"list","ordered":true,"start":2,"spread":false,"position":{"start":{"line":42,"column":1},"end":{"line":42,"column":1}},"children":[{"type":"listItem","spread":true,"position":{"start":{"line":42,"column":1},"end":{"line":42,"column":1}},"children":[{"type":"paragraph","children":[{"type":"text","value":"Define the size of the input signal and allocate memory for the input and output arrays:","position":{"start":{"line":42,"column":1},"end":{"line":42,"column":1}},"key":"qA4G2HrRms"}],"key":"qAkgWvdmJ2"}],"key":"mPJdQBAAwF"}],"key":"T3gSJJjm9b"},{"type":"code","lang":"fortran","value":"integer, parameter :: N = 1024\nreal(c_double), dimension(N) :: x\ncomplex(c_double), dimension(N) :: X","position":{"start":{"line":43,"column":1},"end":{"line":47,"column":1}},"key":"YIlUHFyhy4"},{"type":"list","ordered":true,"start":3,"spread":false,"position":{"start":{"line":48,"column":1},"end":{"line":48,"column":1}},"children":[{"type":"listItem","spread":true,"position":{"start":{"line":48,"column":1},"end":{"line":48,"column":1}},"children":[{"type":"paragraph","children":[{"type":"text","value":"Create a plan for computing the FFT of the input signal:","position":{"start":{"line":48,"column":1},"end":{"line":48,"column":1}},"key":"YFJbpIY62p"}],"key":"xb9j4GdIdx"}],"key":"woVi3qWVhD"}],"key":"LDuUhQMfqx"},{"type":"code","lang":"fortran","value":"type(c_ptr) :: plan\nplan = fftw_plan_dft_1d(N, c_loc(x), c_loc(X), FFTW_FORWARD, FFTW_ESTIMATE)","position":{"start":{"line":49,"column":1},"end":{"line":52,"column":1}},"key":"YQfSkBgRuv"},{"type":"list","ordered":true,"start":4,"spread":false,"position":{"start":{"line":53,"column":1},"end":{"line":53,"column":1}},"children":[{"type":"listItem","spread":true,"position":{"start":{"line":53,"column":1},"end":{"line":53,"column":1}},"children":[{"type":"paragraph","children":[{"type":"text","value":"Generate a sample input signal (e.g., a sinusoidal signal) and compute its DFT:","position":{"start":{"line":53,"column":1},"end":{"line":53,"column":1}},"key":"leu4w8TWfu"}],"key":"ESdUoUji5E"}],"key":"RJXrz76GHL"}],"key":"eYR2EGRMik"},{"type":"code","lang":"fortran","value":"do i = 1, N\n    x(i) = sin(2.0 * 3.14159 * i / N)\nend do\ncall fftw_execute_dft(plan, c_loc(x), c_loc(X))","position":{"start":{"line":54,"column":1},"end":{"line":59,"column":1}},"key":"gY4XLE1c2P"},{"type":"list","ordered":true,"start":5,"spread":false,"position":{"start":{"line":60,"column":1},"end":{"line":60,"column":1}},"children":[{"type":"listItem","spread":true,"position":{"start":{"line":60,"column":1},"end":{"line":60,"column":1}},"children":[{"type":"paragraph","children":[{"type":"text","value":"Visualize the frequency spectrum of the input signal using a plotting library (e.g., gnuplot):","position":{"start":{"line":60,"column":1},"end":{"line":60,"column":1}},"key":"Nq0DNkVgUb"}],"key":"Vwa3fj7Bsq"}],"key":"UXh8MH6IFG"}],"key":"yVGk9PoAeM"},{"type":"code","lang":"fortran","value":"open(unit=10, file='spectrum.dat', status='unknown')\ndo i = 1, N\n    write(10, *) i, abs(X(i))\nend do\nclose(10)","position":{"start":{"line":61,"column":1},"end":{"line":67,"column":1}},"key":"CXVPz3tKCs"},{"type":"list","ordered":true,"start":6,"spread":false,"position":{"start":{"line":68,"column":1},"end":{"line":68,"column":1}},"children":[{"type":"listItem","spread":true,"position":{"start":{"line":68,"column":1},"end":{"line":68,"column":1}},"children":[{"type":"paragraph","children":[{"type":"text","value":"Plot the frequency spectrum using gnuplot:","position":{"start":{"line":68,"column":1},"end":{"line":68,"column":1}},"key":"gUQcx3wK1S"}],"key":"pj6hFsaS2E"}],"key":"PWfapmoNG6"}],"key":"Hg9ZrnNQgi"},{"type":"code","lang":"bash","value":"gnuplot -persist -e \"plot 'spectrum.dat' with lines\"","position":{"start":{"line":69,"column":1},"end":{"line":71,"column":1}},"key":"ADl4jp9R4h"},{"type":"heading","depth":2,"position":{"start":{"line":73,"column":1},"end":{"line":73,"column":1}},"children":[{"type":"text","value":"Discussion","position":{"start":{"line":73,"column":1},"end":{"line":73,"column":1}},"key":"PVW1DiW6si"}],"identifier":"discussion","label":"Discussion","html_id":"discussion","implicit":true,"key":"CdQpe66Hk0"},{"type":"paragraph","position":{"start":{"line":74,"column":1},"end":{"line":74,"column":1}},"children":[{"type":"text","value":"The plan here is to write a Fortran 2003 program that utilizes the FFTW3 library to generate a Discretized Fast Fourier Transforms of arbitrary waveforms. To test the code we start with a function whose DFFT is easily identifiable by inspection, and then increase in complexity. SciLAB and Python+Numpy on Jupyter Notebook are used to generate the the time domain functions, time domain and frequency domain plots and discretized time domain data. The Fortran 2003 code is then run on the discretized time domain data and the results plotted with GNUPlot. A comparison is made to check the veracity of the Fortran 2003 code output.","position":{"start":{"line":74,"column":1},"end":{"line":74,"column":1}},"key":"sUb6nCelYT"}],"key":"ctmYPdfZKm"},{"type":"heading","depth":2,"position":{"start":{"line":76,"column":1},"end":{"line":76,"column":1}},"children":[{"type":"text","value":"Examples","position":{"start":{"line":76,"column":1},"end":{"line":76,"column":1}},"key":"PoqJNzUOp4"}],"identifier":"examples","label":"Examples","html_id":"examples","implicit":true,"key":"UoFFD6PJB9"},{"type":"paragraph","position":{"start":{"line":77,"column":1},"end":{"line":77,"column":1}},"children":[{"type":"text","value":"The following examples demonstrate the computation of the DFT of an arbitrary signal using the FFTW3 library in Fortran.","position":{"start":{"line":77,"column":1},"end":{"line":77,"column":1}},"key":"QQnMqeOGD1"}],"key":"HA3lf7Wjxl"},{"type":"grid","columns":[2,2,2,2],"children":[{"type":"card","url":"Sine_Wave_10_Hz/sine_wave_10_hz.html","children":[{"type":"header","children":[{"type":"paragraph","position":{"start":{"line":87,"column":1},"end":{"line":88,"column":1}},"children":[{"type":"text","value":"Sine Wave at 10 Hz","key":"o4C0tAISOO"}],"key":"p5xBc0nViD"}],"key":"Qq4LbiLJtU"},{"type":"image","url":"/build/sine_wave2_10Hz-49299ad41b3b21d8c987f46d4cd10d3f.jpeg","align":"center","key":"HbV6TzpPdb","urlSource":"images/sine_wave2_10Hz.jpeg"},{"type":"image","url":"/build/DFFT_mag_sine_wave2_-10bfae4afa36239c3ec9755c4b20bdc8.jpeg","align":"center","key":"UL7io95RPf","urlSource":"images/DFFT_mag_sine_wave2_10Hz.jpeg"}],"urlSource":"Sine_Wave_10_Hz/sine_wave_10_hz.html","key":"tFd5CsJqbU"},{"type":"card","url":"Square_Wave_1_Hz_50_pct/square_wave_1_hz_50_pct.html","children":[{"type":"header","children":[{"type":"paragraph","position":{"start":{"line":103,"column":1},"end":{"line":104,"column":1}},"children":[{"type":"text","value":"Square Wave at 1 Hz with 50% Duty Cycle","key":"MeGT5CBXxt"}],"key":"yDz41OZmWh"}],"key":"yCXBTaclx9"},{"type":"image","url":"/build/sq_wave_1Hz_50pct-ab013257d7a82b4ea123e76e73973901.jpeg","align":"center","key":"EMlLKXg8MY","urlSource":"images/sq_wave_1Hz_50pct.jpeg"},{"type":"image","url":"/build/DFFT_mag_sq_wv2_1Hz_-380f7fc22d1e3a2f1b7c86669e5c9d91.jpeg","align":"center","key":"PMFOW9i5bu","urlSource":"images/DFFT_mag_sq_wv2_1Hz_50pct.jpeg"}],"urlSource":"Square_Wave_1_Hz_50_pct/square_wave_1_hz_50_pct.html","key":"FhzEGuMnvE"},{"type":"card","url":"2_Sine_Waves/2sineXHz.html","children":[{"type":"header","children":[{"type":"paragraph","position":{"start":{"line":119,"column":1},"end":{"line":120,"column":1}},"children":[{"type":"text","value":"Two Sine Waves at 50 Hz and 100 Hz","key":"SBi8IbUKRU"}],"key":"V0PgLOhTnd"}],"key":"cnvhXpHwe6"},{"type":"image","url":"/build/2_sine_waves_100_Hz_-2e972a66ce9c62316e0552d300f7f082.png","align":"center","key":"XKwKkF4q8V","urlSource":"images/2_sine_waves_100_Hz_50_Hz.png"},{"type":"image","url":"/build/DFFT_2_sine_waves_10-89995a39218ba1c1e720845ea9a4a97f.png","align":"center","key":"gmj04UnYkU","urlSource":"images/DFFT_2_sine_waves_100_Hz_50_Hz.png"}],"urlSource":"2_Sine_Waves/2sineXHz.html","key":"tg9zh8XMXH"},{"type":"card","url":"Switched_Sine_Wave_1_kHz/switched_sine_wave_1_kHz.html","children":[{"type":"header","children":[{"type":"paragraph","position":{"start":{"line":135,"column":1},"end":{"line":136,"column":1}},"children":[{"type":"text","value":"Switched Sine Wave at 1 kHz","key":"vEN5lOy65a"}],"key":"vVu9te2SMi"}],"key":"jHkU7noZuj"},{"type":"image","url":"/build/switched_sine_wave_1-7713d0151a4e7b3c946c21a02e0310f9.png","align":"center","key":"dCoNNO91rp","urlSource":"images/switched_sine_wave_1_kHz.png"},{"type":"image","url":"/build/DFFT_switched_sine_w-81be2f62e83ba9ad84a41df71b399dea.png","align":"center","key":"IsfPXPsZdh","urlSource":"images/DFFT_switched_sine_wave_1_kHz.png"}],"urlSource":"Switched_Sine_Wave_1_kHz/switched_sine_wave_1_kHz.html","key":"rW4Pg8NlgV"}],"key":"rkRMTHHMjZ"},{"type":"heading","depth":2,"position":{"start":{"line":149,"column":1},"end":{"line":149,"column":1}},"children":[{"type":"text","value":"Conclusion","position":{"start":{"line":149,"column":1},"end":{"line":149,"column":1}},"key":"ebLwgVqq08"}],"identifier":"conclusion","label":"Conclusion","html_id":"conclusion","implicit":true,"key":"pYzRMw5cT1"},{"type":"paragraph","position":{"start":{"line":150,"column":1},"end":{"line":150,"column":1}},"children":[{"type":"text","value":"In this tutorial, we have demonstrated how to compute the Discrete Fourier Transform (DFT) of an arbitrary signal using the FFTW3 library in Fortran. The FFTW3 library provides a fast and efficient way to compute the DFT of a signal and is widely used in scientific computing applications. By following the steps outlined in this tutorial, you can compute the DFT of a signal and visualize its frequency spectrum using the FFTW3 library.","position":{"start":{"line":150,"column":1},"end":{"line":150,"column":1}},"key":"oI3ckAqqR5"}],"key":"OLQR41yzHB"}],"key":"QvMiiGQiV1"}],"key":"m5od0Rs9YI"},"references":{"cite":{"order":[],"data":{}}},"footer":{"navigation":{"prev":{"title":"Neural Fortran Examples: Sine Wave","url":"/sections/computer-programming/fortran/neural-fortran/section-examples-sine-wave","group":"Computer Programming"},"next":{"title":"Sine Wave at 10Hz","url":"/sections/computer-programming/fortran/dfft/sine-wave-10-hz/sine-wave-10-hz","group":"Computer Programming"}}},"domain":"http://localhost:3014"}