{"version":3,"kind":"Article","sha256":"a1a976ca5b20ed0aa5537f8a50d08e5816fbefdac56cdc202381f2080ad289c5","slug":"sections.cybersecurity.disassembling-binaries.c.c","location":"/Sections/Cybersecurity/Disassembling_Binaries/C/c.md","dependencies":[],"frontmatter":{"title":"C","content_includes_title":false,"authors":[{"nameParsed":{"literal":"Mark Khusid","given":"Mark","family":"Khusid"},"name":"Mark Khusid","id":"contributors-myst-generated-uid-0"}],"github":"https://github.com/markkhusid/MKDynamics_Website_V2","numbering":{"title":{"offset":3}},"source_url":"https://github.com/markkhusid/MKDynamics_Website_V2/blob/master/Sections/Cybersecurity/Disassembling_Binaries/C/c.md","edit_url":"https://github.com/markkhusid/MKDynamics_Website_V2/edit/master/Sections/Cybersecurity/Disassembling_Binaries/C/c.md","thumbnail":"/c_splash-7cfbd26191628ba7571fdf44d1a9761d.jpg","thumbnailOptimized":"/c_splash-7cfbd26191628ba7571fdf44d1a9761d.webp","exports":[{"format":"md","filename":"c.md","url":"/c-08b6c7af0b99c84f82d474b2f0883352.md"}]},"mdast":{"type":"root","children":[{"type":"block","children":[{"type":"image","url":"/c_splash-7cfbd26191628ba7571fdf44d1a9761d.jpg","height":"500","width":"800","align":"center","key":"PxWo82rnJj","urlSource":"images/c_splash.jpg","urlOptimized":"/c_splash-7cfbd26191628ba7571fdf44d1a9761d.webp"},{"type":"heading","depth":2,"position":{"start":{"line":8,"column":1},"end":{"line":8,"column":1}},"children":[{"type":"text","value":"Introduction","position":{"start":{"line":8,"column":1},"end":{"line":8,"column":1}},"key":"m6UvpMk0JB"}],"identifier":"introduction","label":"Introduction","html_id":"introduction","implicit":true,"key":"ZR4QME9LBI"},{"type":"paragraph","position":{"start":{"line":9,"column":1},"end":{"line":9,"column":1}},"children":[{"type":"text","value":"C is a general-purpose programming language that was developed in the early 1970s. It is widely used for system programming, embedded systems, and application development. C is known for its efficiency, low-level access to memory, and portability across different platforms.","position":{"start":{"line":9,"column":1},"end":{"line":9,"column":1}},"key":"bLdt20VwWV"}],"key":"lBh1nRzQD9"},{"type":"heading","depth":2,"position":{"start":{"line":11,"column":1},"end":{"line":11,"column":1}},"children":[{"type":"text","value":"Table of Contents","position":{"start":{"line":11,"column":1},"end":{"line":11,"column":1}},"key":"n9PdYsLM4k"}],"identifier":"table-of-contents","label":"Table of Contents","html_id":"table-of-contents","implicit":true,"key":"ibKqYt6JZJ"},{"type":"grid","columns":[1,1,1,1],"children":[{"type":"card","url":"/sections/cybersecurity/disassembling-binaries/c/amd64/amd64-head","children":[{"type":"header","children":[{"type":"paragraph","position":{"start":{"line":22,"column":1},"end":{"line":23,"column":1}},"children":[{"type":"text","value":"C Binaries in AMD64","key":"AuOQIeUXuT"}],"key":"VD5winfJZU"}],"key":"wwFWccaiPV"},{"type":"image","url":"/add_int_C_AMD64_spla-4481e94524e3a21a617d57abcf7baa5a.jpg","height":"500","width":"800","align":"center","key":"zhQ2p7Le7n","urlSource":"images/add_int_C_AMD64_splash.jpg","urlOptimized":"/add_int_C_AMD64_spla-4481e94524e3a21a617d57abcf7baa5a.webp"}],"urlSource":"AMD64/amd64__HEAD__","dataUrl":"/sections.cybersecurity.disassembling-binaries.c.amd64.amd64-head.json","internal":true,"protocol":"file","key":"oNKBY2Btu1"},{"type":"card","url":"/sections/cybersecurity/disassembling-binaries/c/i386/i386-head","children":[{"type":"header","children":[{"type":"paragraph","position":{"start":{"line":35,"column":1},"end":{"line":36,"column":1}},"children":[{"type":"text","value":"C Binaries in i386","key":"UCG3X8QhtE"}],"key":"NIcrllROc6"}],"key":"eUWLb8xila"},{"type":"image","url":"/add_int_C_i386_splas-bbb7228562013327a1ba99cec8524fc2.jpg","height":"500","width":"800","align":"center","key":"Mdq0yTzStd","urlSource":"images/add_int_C_i386_splash.jpg","urlOptimized":"/add_int_C_i386_splas-bbb7228562013327a1ba99cec8524fc2.webp"}],"urlSource":"i386/i386__HEAD__","dataUrl":"/sections.cybersecurity.disassembling-binaries.c.i386.i386-head.json","internal":true,"protocol":"file","key":"LSFnlOA1gs"}],"key":"McubyMbUCC"},{"type":"heading","depth":2,"position":{"start":{"line":44,"column":1},"end":{"line":44,"column":1}},"children":[{"type":"text","value":"Project Code on GitHub","position":{"start":{"line":44,"column":1},"end":{"line":44,"column":1}},"key":"bpsklQmrvw"}],"identifier":"project-code-on-github","label":"Project Code on GitHub","html_id":"project-code-on-github","implicit":true,"key":"mWKPPcbUWY"},{"type":"paragraph","position":{"start":{"line":45,"column":1},"end":{"line":46,"column":1}},"children":[{"type":"text","value":"Project code and resources can be found on my GitHub repository: ","position":{"start":{"line":45,"column":1},"end":{"line":45,"column":1}},"key":"O2YwA3nVuA"},{"type":"break","key":"vaZpqu5NaF"},{"type":"text","value":"\n","position":{"start":{"line":45,"column":1},"end":{"line":45,"column":1}},"key":"XtAV0axLtn"},{"type":"link","url":"https://github.com/markkhusid/Disassembling-Binaries/tree/master/C/Intel_architecture/AMD64","position":{"start":{"line":45,"column":1},"end":{"line":45,"column":1}},"children":[{"type":"text","value":"Github","position":{"start":{"line":45,"column":1},"end":{"line":45,"column":1}},"key":"OXFLa33EDs"}],"urlSource":"https://github.com/markkhusid/Disassembling-Binaries/tree/master/C/Intel_architecture/AMD64","error":true,"key":"NfAmO5BaB9"}],"key":"xTsAPSoGZr"}],"key":"LCFpc8uFzM"}],"key":"cImRzAwVwx"},"references":{"cite":{"order":[],"data":{}}}}